[
  {
    "Name": "Weapon_AK74M",
    "ItemID": "Weapon_AK74M",
    "DisplayName": "NSLOCTEXT(\"Items\", \"AK74M\", \"АК-74М\")",
    "Description": "NSLOCTEXT(\"Items\", \"AK74M_Desc\", \"Модернизированный автомат Калашникова образца 1974 года. Калибр 5.45x39мм.\")",
    "Icon": "",
    "ItemType": "(TagName=\"Item.Weapon.AR\")",
    "Rarity": "(TagName=\"Item.Rarity.Rare\")",
    "ItemTags": "(GameplayTags=((TagName=\"Item.Weapon\"),(TagName=\"Weapon.Type.Ranged\")))",
    "GridSize": "(X=4,Y=2)",
    "MaxStackSize": 1,
    "Weight": 3.4,
    "BaseValue": 38000,
    "bIsEquippable": true,
    "EquipmentSlot": "(TagName=\"Equipment.Slot.PrimaryWeapon\")",
    "bIsConsumable": false,
    "UseTime": 0.0,
    "bCanDrop": true,
    "bCanTrade": true,
    "bIsQuestItem": false,
    "EquipmentActorClass": "/Script/EquipmentSystem.SuspenseCoreWeaponActor",
    "AttachmentSocket": "weapon_r",
    "UnequippedSocket": "spine_03",
    "bIsWeapon": true,
    "WeaponArchetype": "(TagName=\"Weapon.Rifle.Assault\")",
    "AmmoType": "(TagName=\"Item.Ammo.545x39\")",
    "DefaultFireMode": "(TagName=\"Weapon.FireMode.Auto\")",
    "WeaponAttributesRowName": "Weapon_AK74M",
    "ArmorAttributesRowName": "",
    "AmmoAttributesRowName": "",
    "bIsArmor": false,
    "bIsAmmo": false
  },
  {
    "Name": "Weapon_AK103",
    "ItemID": "Weapon_AK103",
    "DisplayName": "NSLOCTEXT(\"Items\", \"AK103\", \"АК-103\")",
    "Description": "NSLOCTEXT(\"Items\", \"AK103_Desc\", \"Автомат Калашникова под патрон 7.62x39мм. Высокая останавливающая сила.\")",
    "Icon": "",
    "ItemType": "(TagName=\"Item.Weapon.AR\")",
    "Rarity": "(TagName=\"Item.Rarity.Rare\")",
    "ItemTags": "(GameplayTags=((TagName=\"Item.Weapon\"),(TagName=\"Weapon.Type.Ranged\")))",
    "GridSize": "(X=4,Y=2)",
    "MaxStackSize": 1,
    "Weight": 3.9,
    "BaseValue": 42000,
    "bIsEquippable": true,
    "EquipmentSlot": "(TagName=\"Equipment.Slot.PrimaryWeapon\")",
    "bIsConsumable": false,
    "UseTime": 0.0,
    "bCanDrop": true,
    "bCanTrade": true,
    "bIsQuestItem": false,
    "EquipmentActorClass": "/Script/EquipmentSystem.SuspenseCoreWeaponActor",
    "AttachmentSocket": "weapon_r",
    "UnequippedSocket": "spine_03",
    "bIsWeapon": true,
    "WeaponArchetype": "(TagName=\"Weapon.Rifle.Assault\")",
    "AmmoType": "(TagName=\"Item.Ammo.762x39\")",
    "DefaultFireMode": "(TagName=\"Weapon.FireMode.Auto\")",
    "WeaponAttributesRowName": "Weapon_AK103",
    "ArmorAttributesRowName": "",
    "AmmoAttributesRowName": "",
    "bIsArmor": false,
    "bIsAmmo": false
  },
  {
    "Name": "Weapon_M4A1",
    "ItemID": "Weapon_M4A1",
    "DisplayName": "NSLOCTEXT(\"Items\", \"M4A1\", \"M4A1\")",
    "Description": "NSLOCTEXT(\"Items\", \"M4A1_Desc\", \"Американская штурмовая винтовка. Калибр 5.56x45мм NATO.\")",
    "Icon": "",
    "ItemType": "(TagName=\"Item.Weapon.AR\")",
    "Rarity": "(TagName=\"Item.Rarity.Rare\")",
    "ItemTags": "(GameplayTags=((TagName=\"Item.Weapon\"),(TagName=\"Weapon.Type.Ranged\")))",
    "GridSize": "(X=4,Y=2)",
    "MaxStackSize": 1,
    "Weight": 3.0,
    "BaseValue": 45000,
    "bIsEquippable": true,
    "EquipmentSlot": "(TagName=\"Equipment.Slot.PrimaryWeapon\")",
    "bIsConsumable": false,
    "UseTime": 0.0,
    "bCanDrop": true,
    "bCanTrade": true,
    "bIsQuestItem": false,
    "EquipmentActorClass": "/Script/EquipmentSystem.SuspenseCoreWeaponActor",
    "AttachmentSocket": "weapon_r",
    "UnequippedSocket": "spine_03",
    "bIsWeapon": true,
    "WeaponArchetype": "(TagName=\"Weapon.Rifle.Assault\")",
    "AmmoType": "(TagName=\"Item.Ammo.556x45\")",
    "DefaultFireMode": "(TagName=\"Weapon.FireMode.Auto\")",
    "WeaponAttributesRowName": "Weapon_M4A1",
    "ArmorAttributesRowName": "",
    "AmmoAttributesRowName": "",
    "bIsArmor": false,
    "bIsAmmo": false
  },
  {
    "Name": "Weapon_MP5SD",
    "ItemID": "Weapon_MP5SD",
    "DisplayName": "NSLOCTEXT(\"Items\", \"MP5SD\", \"MP5SD\")",
    "Description": "NSLOCTEXT(\"Items\", \"MP5SD_Desc\", \"Немецкий пистолет-пулемёт с интегрированным глушителем. Калибр 9x19мм.\")",
    "Icon": "",
    "ItemType": "(TagName=\"Item.Weapon.SMG\")",
    "Rarity": "(TagName=\"Item.Rarity.Rare\")",
    "ItemTags": "(GameplayTags=((TagName=\"Item.Weapon\"),(TagName=\"Weapon.Type.Ranged\")))",
    "GridSize": "(X=4,Y=2)",
    "MaxStackSize": 1,
    "Weight": 3.1,
    "BaseValue": 45000,
    "bIsEquippable": true,
    "EquipmentSlot": "(TagName=\"Equipment.Slot.SecondaryWeapon\")",
    "bIsConsumable": false,
    "UseTime": 0.0,
    "bCanDrop": true,
    "bCanTrade": true,
    "bIsQuestItem": false,
    "EquipmentActorClass": "/Script/EquipmentSystem.SuspenseCoreWeaponActor",
    "AttachmentSocket": "weapon_r",
    "UnequippedSocket": "spine_03",
    "bIsWeapon": true,
    "WeaponArchetype": "(TagName=\"Weapon.SMG.Compact\")",
    "AmmoType": "(TagName=\"Item.Ammo.9x19\")",
    "DefaultFireMode": "(TagName=\"Weapon.FireMode.Auto\")",
    "WeaponAttributesRowName": "Weapon_MP5SD",
    "ArmorAttributesRowName": "",
    "AmmoAttributesRowName": "",
    "bIsArmor": false,
    "bIsAmmo": false
  },
  {
    "Name": "Weapon_MP7A2",
    "ItemID": "Weapon_MP7A2",
    "DisplayName": "NSLOCTEXT(\"Items\", \"MP7A2\", \"MP7A2\")",
    "Description": "NSLOCTEXT(\"Items\", \"MP7A2_Desc\", \"Немецкий PDW от Heckler & Koch. Калибр 4.6x30мм.\")",
    "Icon": "",
    "ItemType": "(TagName=\"Item.Weapon.PDW\")",
    "Rarity": "(TagName=\"Item.Rarity.Epic\")",
    "ItemTags": "(GameplayTags=((TagName=\"Item.Weapon\"),(TagName=\"Weapon.Type.Ranged\")))",
    "GridSize": "(X=3,Y=2)",
    "MaxStackSize": 1,
    "Weight": 1.9,
    "BaseValue": 65000,
    "bIsEquippable": true,
    "EquipmentSlot": "(TagName=\"Equipment.Slot.SecondaryWeapon\")",
    "bIsConsumable": false,
    "UseTime": 0.0,
    "bCanDrop": true,
    "bCanTrade": true,
    "bIsQuestItem": false,
    "EquipmentActorClass": "/Script/EquipmentSystem.SuspenseCoreWeaponActor",
    "AttachmentSocket": "weapon_r",
    "UnequippedSocket": "spine_03",
    "bIsWeapon": true,
    "WeaponArchetype": "(TagName=\"Weapon.PDW.Compact\")",
    "AmmoType": "(TagName=\"Item.Ammo.46x30\")",
    "DefaultFireMode": "(TagName=\"Weapon.FireMode.Auto\")",
    "WeaponAttributesRowName": "Weapon_MP7A2",
    "ArmorAttributesRowName": "",
    "AmmoAttributesRowName": "",
    "bIsArmor": false,
    "bIsAmmo": false
  },
  {
    "Name": "Weapon_Glock17",
    "ItemID": "Weapon_Glock17",
    "DisplayName": "NSLOCTEXT(\"Items\", \"Glock17\", \"Glock 17\")",
    "Description": "NSLOCTEXT(\"Items\", \"Glock17_Desc\", \"Австрийский самозарядный пистолет. Калибр 9x19мм.\")",
    "Icon": "",
    "ItemType": "(TagName=\"Item.Weapon.Pistol\")",
    "Rarity": "(TagName=\"Item.Rarity.Uncommon\")",
    "ItemTags": "(GameplayTags=((TagName=\"Item.Weapon\"),(TagName=\"Weapon.Type.Ranged\")))",
    "GridSize": "(X=2,Y=2)",
    "MaxStackSize": 1,
    "Weight": 0.63,
    "BaseValue": 15000,
    "bIsEquippable": true,
    "EquipmentSlot": "(TagName=\"Equipment.Slot.Holster\")",
    "bIsConsumable": false,
    "UseTime": 0.0,
    "bCanDrop": true,
    "bCanTrade": true,
    "bIsQuestItem": false,
    "EquipmentActorClass": "/Script/EquipmentSystem.SuspenseCoreWeaponActor",
    "AttachmentSocket": "weapon_r",
    "UnequippedSocket": "thigh_r",
    "bIsWeapon": true,
    "WeaponArchetype": "(TagName=\"Weapon.Pistol.Semi\")",
    "AmmoType": "(TagName=\"Item.Ammo.9x19\")",
    "DefaultFireMode": "(TagName=\"Weapon.FireMode.Single\")",
    "WeaponAttributesRowName": "Weapon_Glock17",
    "ArmorAttributesRowName": "",
    "AmmoAttributesRowName": "",
    "bIsArmor": false,
    "bIsAmmo": false
  },
  {
    "Name": "Weapon_M9A3",
    "ItemID": "Weapon_M9A3",
    "DisplayName": "NSLOCTEXT(\"Items\", \"M9A3\", \"Beretta M9A3\")",
    "Description": "NSLOCTEXT(\"Items\", \"M9A3_Desc\", \"Итальянский пистолет. Калибр 9x19мм.\")",
    "Icon": "",
    "ItemType": "(TagName=\"Item.Weapon.Pistol\")",
    "Rarity": "(TagName=\"Item.Rarity.Uncommon\")",
    "ItemTags": "(GameplayTags=((TagName=\"Item.Weapon\"),(TagName=\"Weapon.Type.Ranged\")))",
    "GridSize": "(X=2,Y=2)",
    "MaxStackSize": 1,
    "Weight": 0.94,
    "BaseValue": 18000,
    "bIsEquippable": true,
    "EquipmentSlot": "(TagName=\"Equipment.Slot.Holster\")",
    "bIsConsumable": false,
    "UseTime": 0.0,
    "bCanDrop": true,
    "bCanTrade": true,
    "bIsQuestItem": false,
    "EquipmentActorClass": "/Script/EquipmentSystem.SuspenseCoreWeaponActor",
    "AttachmentSocket": "weapon_r",
    "UnequippedSocket": "thigh_r",
    "bIsWeapon": true,
    "WeaponArchetype": "(TagName=\"Weapon.Pistol.Semi\")",
    "AmmoType": "(TagName=\"Item.Ammo.9x19\")",
    "DefaultFireMode": "(TagName=\"Weapon.FireMode.Single\")",
    "WeaponAttributesRowName": "Weapon_M9A3",
    "ArmorAttributesRowName": "",
    "AmmoAttributesRowName": "",
    "bIsArmor": false,
    "bIsAmmo": false
  },
  {
    "Name": "Weapon_SVD",
    "ItemID": "Weapon_SVD",
    "DisplayName": "NSLOCTEXT(\"Items\", \"SVD\", \"СВД\")",
    "Description": "NSLOCTEXT(\"Items\", \"SVD_Desc\", \"Снайперская винтовка Драгунова. Калибр 7.62x54R.\")",
    "Icon": "",
    "ItemType": "(TagName=\"Item.Weapon.DMR\")",
    "Rarity": "(TagName=\"Item.Rarity.Epic\")",
    "ItemTags": "(GameplayTags=((TagName=\"Item.Weapon\"),(TagName=\"Weapon.Type.Ranged\")))",
    "GridSize": "(X=5,Y=2)",
    "MaxStackSize": 1,
    "Weight": 4.3,
    "BaseValue": 75000,
    "bIsEquippable": true,
    "EquipmentSlot": "(TagName=\"Equipment.Slot.PrimaryWeapon\")",
    "bIsConsumable": false,
    "UseTime": 0.0,
    "bCanDrop": true,
    "bCanTrade": true,
    "bIsQuestItem": false,
    "EquipmentActorClass": "/Script/EquipmentSystem.SuspenseCoreWeaponActor",
    "AttachmentSocket": "weapon_r",
    "UnequippedSocket": "spine_03",
    "bIsWeapon": true,
    "WeaponArchetype": "(TagName=\"Weapon.DMR.Semi\")",
    "AmmoType": "(TagName=\"Item.Ammo.762x54R\")",
    "DefaultFireMode": "(TagName=\"Weapon.FireMode.Single\")",
    "WeaponAttributesRowName": "Weapon_SVD",
    "ArmorAttributesRowName": "",
    "AmmoAttributesRowName": "",
    "bIsArmor": false,
    "bIsAmmo": false
  },
  {
    "Name": "Weapon_M9Bayonet",
    "ItemID": "Weapon_M9Bayonet",
    "DisplayName": "NSLOCTEXT(\"Items\", \"M9Bayonet\", \"Штык-нож M9\")",
    "Description": "NSLOCTEXT(\"Items\", \"M9Bayonet_Desc\", \"Многофункциональный штык-нож армии США.\")",
    "Icon": "",
    "ItemType": "(TagName=\"Item.Weapon.Melee.Knife\")",
    "Rarity": "(TagName=\"Item.Rarity.Common\")",
    "ItemTags": "(GameplayTags=((TagName=\"Item.Weapon\"),(TagName=\"Weapon.Type.Melee\")))",
    "GridSize": "(X=1,Y=2)",
    "MaxStackSize": 1,
    "Weight": 0.34,
    "BaseValue": 8000,
    "bIsEquippable": true,
    "EquipmentSlot": "(TagName=\"Equipment.Slot.Scabbard\")",
    "bIsConsumable": false,
    "UseTime": 0.0,
    "bCanDrop": true,
    "bCanTrade": true,
    "bIsQuestItem": false,
    "EquipmentActorClass": "/Script/EquipmentSystem.SuspenseCoreWeaponActor",
    "AttachmentSocket": "weapon_r",
    "UnequippedSocket": "spine_02",
    "bIsWeapon": true,
    "WeaponArchetype": "(TagName=\"Weapon.Melee.Knife\")",
    "AmmoType": "",
    "DefaultFireMode": "",
    "WeaponAttributesRowName": "Weapon_M9Bayonet",
    "ArmorAttributesRowName": "",
    "AmmoAttributesRowName": "",
    "bIsArmor": false,
    "bIsAmmo": false
  },
  {
    "Name": "Armor_6B47",
    "ItemID": "Armor_6B47",
    "DisplayName": "NSLOCTEXT(\"Items\", \"6B47\", \"Шлем 6Б47 Ратник\")",
    "Description": "NSLOCTEXT(\"Items\", \"6B47_Desc\", \"Современный российский армейский шлем из комплекта Ратник.\")",
    "Icon": "",
    "ItemType": "(TagName=\"Item.Armor.Helmet\")",
    "Rarity": "(TagName=\"Item.Rarity.Rare\")",
    "ItemTags": "(GameplayTags=((TagName=\"Item.Armor\"),(TagName=\"Item.Gear.Headwear\")))",
    "GridSize": "(X=2,Y=2)",
    "MaxStackSize": 1,
    "Weight": 1.0,
    "BaseValue": 42000,
    "bIsEquippable": true,
    "EquipmentSlot": "(TagName=\"Equipment.Slot.Headwear\")",
    "bIsConsumable": false,
    "UseTime": 0.0,
    "bCanDrop": true,
    "bCanTrade": true,
    "bIsQuestItem": false,
    "EquipmentActorClass": "/Script/EquipmentSystem.SuspenseCoreEquipmentActor",
    "AttachmentSocket": "head",
    "UnequippedSocket": "",
    "bIsWeapon": false,
    "WeaponAttributesRowName": "",
    "bIsArmor": true,
    "ArmorType": "(TagName=\"Armor.Type.Head\")",
    "ArmorAttributesRowName": "Helmet_6B47",
    "bIsAmmo": false,
    "AmmoAttributesRowName": ""
  },
  {
    "Name": "Armor_6B13",
    "ItemID": "Armor_6B13",
    "DisplayName": "NSLOCTEXT(\"Items\", \"6B13\", \"Бронежилет 6Б13\")",
    "Description": "NSLOCTEXT(\"Items\", \"6B13_Desc\", \"Российский армейский бронежилет с защитой класса 4.\")",
    "Icon": "",
    "ItemType": "(TagName=\"Item.Armor.BodyArmor\")",
    "Rarity": "(TagName=\"Item.Rarity.Rare\")",
    "ItemTags": "(GameplayTags=((TagName=\"Item.Armor\")))",
    "GridSize": "(X=3,Y=3)",
    "MaxStackSize": 1,
    "Weight": 8.5,
    "BaseValue": 85000,
    "bIsEquippable": true,
    "EquipmentSlot": "(TagName=\"Equipment.Slot.BodyArmor\")",
    "bIsConsumable": false,
    "UseTime": 0.0,
    "bCanDrop": true,
    "bCanTrade": true,
    "bIsQuestItem": false,
    "EquipmentActorClass": "/Script/EquipmentSystem.SuspenseCoreEquipmentActor",
    "AttachmentSocket": "spine_03",
    "UnequippedSocket": "",
    "bIsWeapon": false,
    "WeaponAttributesRowName": "",
    "bIsArmor": true,
    "ArmorType": "(TagName=\"Armor.Type.Body\")",
    "ArmorAttributesRowName": "Armor_6B13",
    "bIsAmmo": false,
    "AmmoAttributesRowName": ""
  },
  {
    "Name": "Armor_Slick",
    "ItemID": "Armor_Slick",
    "DisplayName": "NSLOCTEXT(\"Items\", \"Slick\", \"LBT 6094A Slick\")",
    "Description": "NSLOCTEXT(\"Items\", \"Slick_Desc\", \"Высококлассный плейткарриер с защитой класса 6.\")",
    "Icon": "",
    "ItemType": "(TagName=\"Item.Armor.BodyArmor\")",
    "Rarity": "(TagName=\"Item.Rarity.Epic\")",
    "ItemTags": "(GameplayTags=((TagName=\"Item.Armor\")))",
    "GridSize": "(X=3,Y=3)",
    "MaxStackSize": 1,
    "Weight": 5.5,
    "BaseValue": 180000,
    "bIsEquippable": true,
    "EquipmentSlot": "(TagName=\"Equipment.Slot.BodyArmor\")",
    "bIsConsumable": false,
    "UseTime": 0.0,
    "bCanDrop": true,
    "bCanTrade": true,
    "bIsQuestItem": false,
    "EquipmentActorClass": "/Script/EquipmentSystem.SuspenseCoreEquipmentActor",
    "AttachmentSocket": "spine_03",
    "UnequippedSocket": "",
    "bIsWeapon": false,
    "WeaponAttributesRowName": "",
    "bIsArmor": true,
    "ArmorType": "(TagName=\"Armor.Type.Body\")",
    "ArmorAttributesRowName": "Armor_SlickPlate",
    "bIsAmmo": false,
    "AmmoAttributesRowName": ""
  },
  {
    "Name": "Helmet_Altyn",
    "ItemID": "Helmet_Altyn",
    "DisplayName": "NSLOCTEXT(\"Items\", \"Altyn\", \"Шлем Алтын\")",
    "Description": "NSLOCTEXT(\"Items\", \"Altyn_Desc\", \"Тяжёлый бронешлем с забралом. Защита класса 5.\")",
    "Icon": "",
    "ItemType": "(TagName=\"Item.Armor.Helmet\")",
    "Rarity": "(TagName=\"Item.Rarity.Epic\")",
    "ItemTags": "(GameplayTags=((TagName=\"Item.Armor\"),(TagName=\"Item.Gear.Headwear\")))",
    "GridSize": "(X=2,Y=2)",
    "MaxStackSize": 1,
    "Weight": 2.8,
    "BaseValue": 95000,
    "bIsEquippable": true,
    "EquipmentSlot": "(TagName=\"Equipment.Slot.Headwear\")",
    "bIsConsumable": false,
    "UseTime": 0.0,
    "bCanDrop": true,
    "bCanTrade": true,
    "bIsQuestItem": false,
    "EquipmentActorClass": "/Script/EquipmentSystem.SuspenseCoreEquipmentActor",
    "AttachmentSocket": "head",
    "UnequippedSocket": "",
    "bIsWeapon": false,
    "WeaponAttributesRowName": "",
    "bIsArmor": true,
    "ArmorType": "(TagName=\"Armor.Type.Head\")",
    "ArmorAttributesRowName": "Helmet_Altyn",
    "bIsAmmo": false,
    "AmmoAttributesRowName": ""
  },
  {
    "Name": "Ammo_545x39_PS",
    "ItemID": "Ammo_545x39_PS",
    "DisplayName": "NSLOCTEXT(\"Items\", \"545x39_PS\", \"5.45x39мм ПС гс\")",
    "Description": "NSLOCTEXT(\"Items\", \"545x39_PS_Desc\", \"Стандартный патрон для АК-74. Стальной сердечник.\")",
    "Icon": "",
    "ItemType": "(TagName=\"Item.Ammo.Rifle\")",
    "Rarity": "(TagName=\"Item.Rarity.Common\")",
    "ItemTags": "(GameplayTags=((TagName=\"Item.Ammo\")))",
    "GridSize": "(X=1,Y=1)",
    "MaxStackSize": 60,
    "Weight": 0.010,
    "BaseValue": 85,
    "bIsEquippable": false,
    "EquipmentSlot": "",
    "bIsConsumable": false,
    "UseTime": 0.0,
    "bCanDrop": true,
    "bCanTrade": true,
    "bIsQuestItem": false,
    "bIsWeapon": false,
    "WeaponAttributesRowName": "",
    "bIsArmor": false,
    "ArmorAttributesRowName": "",
    "bIsAmmo": true,
    "AmmoCaliber": "(TagName=\"Item.Ammo.545x39\")",
    "CompatibleWeapons": "(GameplayTags=((TagName=\"Weapon.Type.AK74\"),(TagName=\"Weapon.Type.AK74M\")))",
    "AmmoAttributesRowName": "Ammo_545x39_PS"
  },
  {
    "Name": "Ammo_545x39_BP",
    "ItemID": "Ammo_545x39_BP",
    "DisplayName": "NSLOCTEXT(\"Items\", \"545x39_BP\", \"5.45x39мм БП\")",
    "Description": "NSLOCTEXT(\"Items\", \"545x39_BP_Desc\", \"Бронебойный патрон. Повышенное пробитие брони.\")",
    "Icon": "",
    "ItemType": "(TagName=\"Item.Ammo.Rifle\")",
    "Rarity": "(TagName=\"Item.Rarity.Rare\")",
    "ItemTags": "(GameplayTags=((TagName=\"Item.Ammo\")))",
    "GridSize": "(X=1,Y=1)",
    "MaxStackSize": 60,
    "Weight": 0.010,
    "BaseValue": 350,
    "bIsEquippable": false,
    "EquipmentSlot": "",
    "bIsConsumable": false,
    "UseTime": 0.0,
    "bCanDrop": true,
    "bCanTrade": true,
    "bIsQuestItem": false,
    "bIsWeapon": false,
    "WeaponAttributesRowName": "",
    "bIsArmor": false,
    "ArmorAttributesRowName": "",
    "bIsAmmo": true,
    "AmmoCaliber": "(TagName=\"Item.Ammo.545x39\")",
    "CompatibleWeapons": "(GameplayTags=((TagName=\"Weapon.Type.AK74\"),(TagName=\"Weapon.Type.AK74M\")))",
    "AmmoAttributesRowName": "Ammo_545x39_BP"
  },
  {
    "Name": "Ammo_556x45_M855A1",
    "ItemID": "Ammo_556x45_M855A1",
    "DisplayName": "NSLOCTEXT(\"Items\", \"556x45_M855A1\", \"5.56x45мм M855A1\")",
    "Description": "NSLOCTEXT(\"Items\", \"556x45_M855A1_Desc\", \"Улучшенный патрон NATO с повышенной бронепробиваемостью.\")",
    "Icon": "",
    "ItemType": "(TagName=\"Item.Ammo.Rifle\")",
    "Rarity": "(TagName=\"Item.Rarity.Rare\")",
    "ItemTags": "(GameplayTags=((TagName=\"Item.Ammo\")))",
    "GridSize": "(X=1,Y=1)",
    "MaxStackSize": 60,
    "Weight": 0.012,
    "BaseValue": 400,
    "bIsEquippable": false,
    "EquipmentSlot": "",
    "bIsConsumable": false,
    "UseTime": 0.0,
    "bCanDrop": true,
    "bCanTrade": true,
    "bIsQuestItem": false,
    "bIsWeapon": false,
    "WeaponAttributesRowName": "",
    "bIsArmor": false,
    "ArmorAttributesRowName": "",
    "bIsAmmo": true,
    "AmmoCaliber": "(TagName=\"Item.Ammo.556x45\")",
    "CompatibleWeapons": "(GameplayTags=((TagName=\"Weapon.Type.M4A1\"),(TagName=\"Weapon.Type.HK416\")))",
    "AmmoAttributesRowName": "Ammo_556x45_M855A1"
  },
  {
    "Name": "Ammo_9x19_PST",
    "ItemID": "Ammo_9x19_PST",
    "DisplayName": "NSLOCTEXT(\"Items\", \"9x19_PST\", \"9x19мм ПСТ гж\")",
    "Description": "NSLOCTEXT(\"Items\", \"9x19_PST_Desc\", \"Пистолетный патрон со стальным сердечником.\")",
    "Icon": "",
    "ItemType": "(TagName=\"Item.Ammo.Pistol\")",
    "Rarity": "(TagName=\"Item.Rarity.Common\")",
    "ItemTags": "(GameplayTags=((TagName=\"Item.Ammo\")))",
    "GridSize": "(X=1,Y=1)",
    "MaxStackSize": 50,
    "Weight": 0.008,
    "BaseValue": 45,
    "bIsEquippable": false,
    "EquipmentSlot": "",
    "bIsConsumable": false,
    "UseTime": 0.0,
    "bCanDrop": true,
    "bCanTrade": true,
    "bIsQuestItem": false,
    "bIsWeapon": false,
    "WeaponAttributesRowName": "",
    "bIsArmor": false,
    "ArmorAttributesRowName": "",
    "bIsAmmo": true,
    "AmmoCaliber": "(TagName=\"Item.Ammo.9x19\")",
    "CompatibleWeapons": "(GameplayTags=((TagName=\"Weapon.Type.Glock17\"),(TagName=\"Weapon.Type.MP5\")))",
    "AmmoAttributesRowName": "Ammo_9x19_PST"
  },
  {
    "Name": "Ammo_762x54R_LPS",
    "ItemID": "Ammo_762x54R_LPS",
    "DisplayName": "NSLOCTEXT(\"Items\", \"762x54R_LPS\", \"7.62x54R ЛПС гж\")",
    "Description": "NSLOCTEXT(\"Items\", \"762x54R_LPS_Desc\", \"Стандартный винтовочный патрон для СВД.\")",
    "Icon": "",
    "ItemType": "(TagName=\"Item.Ammo.Rifle\")",
    "Rarity": "(TagName=\"Item.Rarity.Uncommon\")",
    "ItemTags": "(GameplayTags=((TagName=\"Item.Ammo\")))",
    "GridSize": "(X=1,Y=1)",
    "MaxStackSize": 40,
    "Weight": 0.022,
    "BaseValue": 250,
    "bIsEquippable": false,
    "EquipmentSlot": "",
    "bIsConsumable": false,
    "UseTime": 0.0,
    "bCanDrop": true,
    "bCanTrade": true,
    "bIsQuestItem": false,
    "bIsWeapon": false,
    "WeaponAttributesRowName": "",
    "bIsArmor": false,
    "ArmorAttributesRowName": "",
    "bIsAmmo": true,
    "AmmoCaliber": "(TagName=\"Item.Ammo.762x54R\")",
    "CompatibleWeapons": "(GameplayTags=((TagName=\"Weapon.Type.SVD\")))",
    "AmmoAttributesRowName": "Ammo_762x54R_LPS"
  },
  {
    "Name": "Gear_TV110",
    "ItemID": "Gear_TV110",
    "DisplayName": "NSLOCTEXT(\"Items\", \"TV110\", \"Разгрузка TV-110\")",
    "Description": "NSLOCTEXT(\"Items\", \"TV110_Desc\", \"Модульная тактическая разгрузка Velocity Systems.\")",
    "Icon": "",
    "ItemType": "(TagName=\"Item.Gear.TacticalRig\")",
    "Rarity": "(TagName=\"Item.Rarity.Uncommon\")",
    "ItemTags": "(GameplayTags=((TagName=\"Item.Gear\")))",
    "GridSize": "(X=2,Y=3)",
    "MaxStackSize": 1,
    "Weight": 1.8,
    "BaseValue": 35000,
    "bIsEquippable": true,
    "EquipmentSlot": "(TagName=\"Equipment.Slot.TacticalRig\")",
    "bIsConsumable": false,
    "UseTime": 0.0,
    "bCanDrop": true,
    "bCanTrade": true,
    "bIsQuestItem": false,
    "EquipmentActorClass": "/Script/EquipmentSystem.SuspenseCoreEquipmentActor",
    "AttachmentSocket": "spine_03",
    "UnequippedSocket": "",
    "bIsWeapon": false,
    "WeaponAttributesRowName": "",
    "bIsArmor": false,
    "ArmorAttributesRowName": "",
    "bIsAmmo": false,
    "AmmoAttributesRowName": ""
  },
  {
    "Name": "Gear_BergenBackpack",
    "ItemID": "Gear_BergenBackpack",
    "DisplayName": "NSLOCTEXT(\"Items\", \"Bergen\", \"Рюкзак Bergen\")",
    "Description": "NSLOCTEXT(\"Items\", \"Bergen_Desc\", \"Тактический рюкзак большой вместимости (65л).\")",
    "Icon": "",
    "ItemType": "(TagName=\"Item.Gear.Backpack\")",
    "Rarity": "(TagName=\"Item.Rarity.Rare\")",
    "ItemTags": "(GameplayTags=((TagName=\"Item.Gear\")))",
    "GridSize": "(X=3,Y=3)",
    "MaxStackSize": 1,
    "Weight": 2.5,
    "BaseValue": 48000,
    "bIsEquippable": true,
    "EquipmentSlot": "(TagName=\"Equipment.Slot.Backpack\")",
    "bIsConsumable": false,
    "UseTime": 0.0,
    "bCanDrop": true,
    "bCanTrade": true,
    "bIsQuestItem": false,
    "EquipmentActorClass": "/Script/EquipmentSystem.SuspenseCoreEquipmentActor",
    "AttachmentSocket": "spine_02",
    "UnequippedSocket": "",
    "bIsWeapon": false,
    "WeaponAttributesRowName": "",
    "bIsArmor": false,
    "ArmorAttributesRowName": "",
    "bIsAmmo": false,
    "AmmoAttributesRowName": ""
  },
  {
    "Name": "Medical_IFAK",
    "ItemID": "Medical_IFAK",
    "DisplayName": "NSLOCTEXT(\"Items\", \"IFAK\", \"IFAK\")",
    "Description": "NSLOCTEXT(\"Items\", \"IFAK_Desc\", \"Индивидуальная аптечка первой помощи.\")",
    "Icon": "",
    "ItemType": "(TagName=\"Item.Consumable.Medical\")",
    "Rarity": "(TagName=\"Item.Rarity.Uncommon\")",
    "ItemTags": "(GameplayTags=((TagName=\"Item.Consumable\"),(TagName=\"Item.Medical\")))",
    "GridSize": "(X=1,Y=2)",
    "MaxStackSize": 1,
    "Weight": 0.3,
    "BaseValue": 15000,
    "bIsEquippable": true,
    "EquipmentSlot": "(TagName=\"Equipment.Slot.QuickSlot1\")",
    "bIsConsumable": true,
    "UseTime": 5.0,
    "bCanDrop": true,
    "bCanTrade": true,
    "bIsQuestItem": false,
    "bIsWeapon": false,
    "WeaponAttributesRowName": "",
    "bIsArmor": false,
    "ArmorAttributesRowName": "",
    "bIsAmmo": false,
    "AmmoAttributesRowName": ""
  },
  {
    "Name": "Throwable_F1",
    "ItemID": "Throwable_F1",
    "DisplayName": "NSLOCTEXT(\"Items\", \"F1\", \"Граната Ф-1\")",
    "Description": "NSLOCTEXT(\"Items\", \"F1_Desc\", \"Оборонительная ручная граната. Радиус поражения 20м.\")",
    "Icon": "",
    "ItemType": "(TagName=\"Item.Throwable\")",
    "Rarity": "(TagName=\"Item.Rarity.Uncommon\")",
    "ItemTags": "(GameplayTags=((TagName=\"Item.Throwable\")))",
    "GridSize": "(X=1,Y=1)",
    "MaxStackSize": 1,
    "Weight": 0.6,
    "BaseValue": 8000,
    "bIsEquippable": true,
    "EquipmentSlot": "(TagName=\"Equipment.Slot.QuickSlot2\")",
    "bIsConsumable": false,
    "UseTime": 0.0,
    "bCanDrop": true,
    "bCanTrade": true,
    "bIsQuestItem": false,
    "bIsWeapon": false,
    "WeaponAttributesRowName": "",
    "bIsArmor": false,
    "ArmorAttributesRowName": "",
    "bIsAmmo": false,
    "AmmoAttributesRowName": ""
  }
]
